{
  "textHash": "039ed85b6eb188",
  "key": "event.unionMoratoriumDemand.body",
  "model": "eleven_multilingual_v2",
  "text": "The largest logistics union in the country is threatening a nationwide walkout. Their demand is simple: freeze warehouse automation for eighteen months or they strike. Members already lost eleven thousand jobs to sorting robots this year. Half of next quarter's automation savings were supposed to come from those warehouses.",
  "alignment": {
    "characters": [
      "T",
      "h",
      "e",
      " ",
      "l",
      "a",
      "r",
      "g",
      "e",
      "s",
      "t",
      " ",
      "l",
      "o",
      "g",
      "i",
      "s",
      "t",
      "i",
      "c",
      "s",
      " ",
      "u",
      "n",
      "i",
      "o",
      "n",
      " ",
      "i",
      "n",
      " ",
      "t",
      "h",
      "e",
      " ",
      "c",
      "o",
      "u",
      "n",
      "t",
      "r",
      "y",
      " ",
      "i",
      "s",
      " ",
      "t",
      "h",
      "r",
      "e",
      "a",
      "t",
      "e",
      "n",
      "i",
      "n",
      "g",
      " ",
      "a",
      " ",
      "n",
      "a",
      "t",
      "i",
      "o",
      "n",
      "w",
      "i",
      "d",
      "e",
      " ",
      "w",
      "a",
      "l",
      "k",
      "o",
      "u",
      "t",
      ".",
      " ",
      "T",
      "h",
      "e",
      "i",
      "r",
      " ",
      "d",
      "e",
      "m",
      "a",
      "n",
      "d",
      " ",
      "i",
      "s",
      " ",
      "s",
      "i",
      "m",
      "p",
      "l",
      "e",
      ":",
      " ",
      "f",
      "r",
      "e",
      "e",
      "z",
      "e",
      " ",
      "w",
      "a",
      "r",
      "e",
      "h",
      "o",
      "u",
      "s",
      "e",
      " ",
      "a",
      "u",
      "t",
      "o",
      "m",
      "a",
      "t",
      "i",
      "o",
      "n",
      " ",
      "f",
      "o",
      "r",
      " ",
      "e",
      "i",
      "g",
      "h",
      "t",
      "e",
      "e",
      "n",
      " ",
      "m",
      "o",
      "n",
      "t",
      "h",
      "s",
      " ",
      "o",
      "r",
      " ",
      "t",
      "h",
      "e",
      "y",
      " ",
      "s",
      "t",
      "r",
      "i",
      "k",
      "e",
      ".",
      " ",
      "M",
      "e",
      "m",
      "b",
      "e",
      "r",
      "s",
      " ",
      "a",
      "l",
      "r",
      "e",
      "a",
      "d",
      "y",
      " ",
      "l",
      "o",
      "s",
      "t",
      " ",
      "e",
      "l",
      "e",
      "v",
      "e",
      "n",
      " ",
      "t",
      "h",
      "o",
      "u",
      "s",
      "a",
      "n",
      "d",
      " ",
      "j",
      "o",
      "b",
      "s",
      " ",
      "t",
      "o",
      " ",
      "s",
      "o",
      "r",
      "t",
      "i",
      "n",
      "g",
      " ",
      "r",
      "o",
      "b",
      "o",
      "t",
      "s",
      " ",
      "t",
      "h",
      "i",
      "s",
      " ",
      "y",
      "e",
      "a",
      "r",
      ".",
      " ",
      "H",
      "a",
      "l",
      "f",
      " ",
      "o",
      "f",
      " ",
      "n",
      "e",
      "x",
      "t",
      " ",
      "q",
      "u",
      "a",
      "r",
      "t",
      "e",
      "r",
      "'",
      "s",
      " ",
      "a",
      "u",
      "t",
      "o",
      "m",
      "a",
      "t",
      "i",
      "o",
      "n",
      " ",
      "s",
      "a",
      "v",
      "i",
      "n",
      "g",
      "s",
      " ",
      "w",
      "e",
      "r",
      "e",
      " ",
      "s",
      "u",
      "p",
      "p",
      "o",
      "s",
      "e",
      "d",
      " ",
      "t",
      "o",
      " ",
      "c",
      "o",
      "m",
      "e",
      " ",
      "f",
      "r",
      "o",
      "m",
      " ",
      "t",
      "h",
      "o",
      "s",
      "e",
      " ",
      "w",
      "a",
      "r",
      "e",
      "h",
      "o",
      "u",
      "s",
      "e",
      "s",
      "."
    ],
    "character_start_times_seconds": [
      0,
      0.07,
      0.139,
      0.197,
      0.279,
      0.325,
      0.395,
      0.453,
      0.511,
      0.604,
      0.65,
      0.697,
      0.766,
      0.801,
      0.882,
      0.964,
      1.08,
      1.138,
      1.207,
      1.289,
      1.347,
      1.405,
      1.498,
      1.567,
      1.637,
      1.695,
      1.73,
      1.765,
      1.811,
      1.846,
      1.869,
      1.916,
      1.939,
      1.962,
      1.985,
      2.032,
      2.067,
      2.113,
      2.148,
      2.206,
      2.264,
      2.345,
      2.473,
      2.914,
      3.042,
      3.088,
      3.158,
      3.181,
      3.239,
      3.286,
      3.32,
      3.367,
      3.425,
      3.471,
      3.529,
      3.587,
      3.622,
      3.657,
      3.738,
      3.785,
      3.901,
      3.959,
      4.052,
      4.11,
      4.168,
      4.214,
      4.272,
      4.354,
      4.505,
      4.551,
      4.598,
      4.632,
      4.679,
      4.748,
      4.818,
      4.899,
      4.992,
      5.05,
      5.178,
      5.387,
      5.991,
      6.037,
      6.095,
      6.142,
      6.188,
      6.211,
      6.258,
      6.293,
      6.351,
      6.42,
      6.536,
      6.594,
      6.711,
      6.827,
      6.978,
      7.012,
      7.07,
      7.117,
      7.175,
      7.233,
      7.303,
      7.372,
      7.581,
      7.639,
      8.336,
      8.417,
      8.487,
      8.557,
      8.615,
      8.661,
      8.696,
      8.742,
      8.777,
      8.87,
      8.916,
      8.951,
      9.009,
      9.056,
      9.102,
      9.149,
      9.195,
      9.23,
      9.276,
      9.346,
      9.392,
      9.451,
      9.509,
      9.59,
      9.648,
      9.694,
      9.741,
      9.787,
      9.857,
      9.903,
      9.95,
      9.985,
      10.043,
      10.089,
      10.136,
      10.17,
      10.205,
      10.252,
      10.321,
      10.379,
      10.414,
      10.472,
      10.519,
      10.588,
      10.635,
      10.681,
      10.728,
      10.844,
      11.227,
      11.343,
      11.378,
      11.424,
      11.447,
      11.471,
      11.505,
      11.552,
      11.598,
      11.633,
      11.691,
      11.749,
      11.831,
      11.9,
      12.074,
      12.132,
      12.829,
      12.899,
      12.957,
      13.003,
      13.05,
      13.096,
      13.131,
      13.189,
      13.235,
      13.282,
      13.351,
      13.41,
      13.444,
      13.479,
      13.526,
      13.572,
      13.63,
      13.677,
      13.758,
      13.827,
      13.874,
      13.932,
      13.99,
      14.048,
      14.106,
      14.153,
      14.211,
      14.245,
      14.303,
      14.327,
      14.385,
      14.443,
      14.501,
      14.559,
      14.605,
      14.64,
      14.663,
      14.733,
      14.779,
      14.93,
      15,
      15.047,
      15.093,
      15.128,
      15.163,
      15.232,
      15.279,
      15.372,
      15.418,
      15.464,
      15.511,
      15.534,
      15.557,
      15.604,
      15.639,
      15.732,
      15.801,
      15.882,
      15.94,
      15.986,
      16.021,
      16.044,
      16.091,
      16.137,
      16.172,
      16.219,
      16.265,
      16.312,
      16.346,
      16.462,
      16.637,
      17.333,
      17.414,
      17.507,
      17.577,
      17.635,
      17.716,
      17.751,
      17.786,
      17.879,
      17.925,
      17.995,
      18.065,
      18.111,
      18.169,
      18.204,
      18.262,
      18.308,
      18.355,
      18.401,
      18.448,
      18.483,
      18.517,
      18.541,
      18.599,
      18.668,
      18.726,
      18.773,
      18.831,
      18.901,
      18.993,
      19.051,
      19.11,
      19.168,
      19.202,
      19.295,
      19.365,
      19.516,
      19.586,
      19.667,
      19.69,
      19.748,
      19.806,
      19.841,
      19.864,
      19.911,
      19.934,
      19.957,
      19.98,
      20.003,
      20.038,
      20.085,
      20.131,
      20.189,
      20.224,
      20.271,
      20.294,
      20.317,
      20.34,
      20.363,
      20.433,
      20.491,
      20.572,
      20.63,
      20.688,
      20.735,
      20.781,
      20.816,
      20.851,
      20.886,
      20.944,
      20.967,
      21.014,
      21.072,
      21.13,
      21.164,
      21.211,
      21.246,
      21.339,
      21.397,
      21.443,
      21.513,
      21.571,
      21.617,
      21.687,
      21.803,
      21.919
    ],
    "character_end_times_seconds": [
      0.07,
      0.139,
      0.197,
      0.279,
      0.325,
      0.395,
      0.453,
      0.511,
      0.604,
      0.65,
      0.697,
      0.766,
      0.801,
      0.882,
      0.964,
      1.08,
      1.138,
      1.207,
      1.289,
      1.347,
      1.405,
      1.498,
      1.567,
      1.637,
      1.695,
      1.73,
      1.765,
      1.811,
      1.846,
      1.869,
      1.916,
      1.939,
      1.962,
      1.985,
      2.032,
      2.067,
      2.113,
      2.148,
      2.206,
      2.264,
      2.345,
      2.473,
      2.914,
      3.042,
      3.088,
      3.158,
      3.181,
      3.239,
      3.286,
      3.32,
      3.367,
      3.425,
      3.471,
      3.529,
      3.587,
      3.622,
      3.657,
      3.738,
      3.785,
      3.901,
      3.959,
      4.052,
      4.11,
      4.168,
      4.214,
      4.272,
      4.354,
      4.505,
      4.551,
      4.598,
      4.632,
      4.679,
      4.748,
      4.818,
      4.899,
      4.992,
      5.05,
      5.178,
      5.387,
      5.991,
      6.037,
      6.095,
      6.142,
      6.188,
      6.211,
      6.258,
      6.293,
      6.351,
      6.42,
      6.536,
      6.594,
      6.711,
      6.827,
      6.978,
      7.012,
      7.07,
      7.117,
      7.175,
      7.233,
      7.303,
      7.372,
      7.581,
      7.639,
      8.336,
      8.417,
      8.487,
      8.557,
      8.615,
      8.661,
      8.696,
      8.742,
      8.777,
      8.87,
      8.916,
      8.951,
      9.009,
      9.056,
      9.102,
      9.149,
      9.195,
      9.23,
      9.276,
      9.346,
      9.392,
      9.451,
      9.509,
      9.59,
      9.648,
      9.694,
      9.741,
      9.787,
      9.857,
      9.903,
      9.95,
      9.985,
      10.043,
      10.089,
      10.136,
      10.17,
      10.205,
      10.252,
      10.321,
      10.379,
      10.414,
      10.472,
      10.519,
      10.588,
      10.635,
      10.681,
      10.728,
      10.844,
      11.227,
      11.343,
      11.378,
      11.424,
      11.447,
      11.471,
      11.505,
      11.552,
      11.598,
      11.633,
      11.691,
      11.749,
      11.831,
      11.9,
      12.074,
      12.132,
      12.829,
      12.899,
      12.957,
      13.003,
      13.05,
      13.096,
      13.131,
      13.189,
      13.235,
      13.282,
      13.351,
      13.41,
      13.444,
      13.479,
      13.526,
      13.572,
      13.63,
      13.677,
      13.758,
      13.827,
      13.874,
      13.932,
      13.99,
      14.048,
      14.106,
      14.153,
      14.211,
      14.245,
      14.303,
      14.327,
      14.385,
      14.443,
      14.501,
      14.559,
      14.605,
      14.64,
      14.663,
      14.733,
      14.779,
      14.93,
      15,
      15.047,
      15.093,
      15.128,
      15.163,
      15.232,
      15.279,
      15.372,
      15.418,
      15.464,
      15.511,
      15.534,
      15.557,
      15.604,
      15.639,
      15.732,
      15.801,
      15.882,
      15.94,
      15.986,
      16.021,
      16.044,
      16.091,
      16.137,
      16.172,
      16.219,
      16.265,
      16.312,
      16.346,
      16.462,
      16.637,
      17.333,
      17.414,
      17.507,
      17.577,
      17.635,
      17.716,
      17.751,
      17.786,
      17.879,
      17.925,
      17.995,
      18.065,
      18.111,
      18.169,
      18.204,
      18.262,
      18.308,
      18.355,
      18.401,
      18.448,
      18.483,
      18.517,
      18.541,
      18.599,
      18.668,
      18.726,
      18.773,
      18.831,
      18.901,
      18.993,
      19.051,
      19.11,
      19.168,
      19.202,
      19.295,
      19.365,
      19.516,
      19.586,
      19.667,
      19.69,
      19.748,
      19.806,
      19.841,
      19.864,
      19.911,
      19.934,
      19.957,
      19.98,
      20.003,
      20.038,
      20.085,
      20.131,
      20.189,
      20.224,
      20.271,
      20.294,
      20.317,
      20.34,
      20.363,
      20.433,
      20.491,
      20.572,
      20.63,
      20.688,
      20.735,
      20.781,
      20.816,
      20.851,
      20.886,
      20.944,
      20.967,
      21.014,
      21.072,
      21.13,
      21.164,
      21.211,
      21.246,
      21.339,
      21.397,
      21.443,
      21.513,
      21.571,
      21.617,
      21.687,
      21.803,
      21.919,
      22.198
    ]
  }
}
